mcp_obsidian_remote/__init__.py
mcp_obsidian_remote/__main__.py
mcp_obsidian_remote/obsidian.py
mcp_obsidian_remote/server.py
mcp_obsidian_remote/tools.py
mcp_obsidian_remote-0.2.3.dist-info/METADATA
mcp_obsidian_remote-0.2.3.dist-info/WHEEL
mcp_obsidian_remote-0.2.3.dist-info/entry_points.txt
mcp_obsidian_remote-0.2.3.dist-info/licenses/LICENSE
mcp_obsidian_remote-0.2.3.dist-info/RECORD
