Metadata-Version: 2.4
Name: mcp-obsidian-remote
Version: 0.2.3
Summary: MCP server to work with Obsidian remotely via REST plugin
Author-email: Markus Pfundstein <markus@life-electronic.nl>, Alexei Smirnov <alexei@virtuman.com>
License-File: LICENSE
Requires-Python: >=3.11
Requires-Dist: mcp>=1.1.0
Requires-Dist: python-dotenv>=1.0.1
Requires-Dist: requests>=2.32.3
